setup.cfg
setup.py
bin/kargo
src/kargo/__init__.py
src/kargo/cloud.py
src/kargo/common.py
src/kargo/configure.py
src/kargo/deploy.py
src/kargo/inventory.py
src/kargo.egg-info/PKG-INFO
src/kargo.egg-info/SOURCES.txt
src/kargo.egg-info/dependency_links.txt
src/kargo.egg-info/not-zip-safe
src/kargo.egg-info/requires.txt
src/kargo.egg-info/top_level.txt
src/kargo/files/.kargo.yml
src/kargo/files/kargo.yml