Metadata-Version: 1.1
Name: kargo
Version: 0.4.8
Summary: Kargo kubernetes cluster deployment
Home-page: https://github.com/kubespray/kargo-cli
Author: Smaine Kahlouch
Author-email: smainklh@gmail.com
License: GPLv3
Keywords: kargo
Platform: UNKNOWN
Classifier: Development Status :: 2 - Pre-Alpha
Classifier: Intended Audience :: Developers
Classifier: Natural Language :: English
Classifier: Programming Language :: Python :: 2
Classifier: Programming Language :: Python :: 2.7
